[{"caption":{"id":"0c85efed","orderNo":441,"movieId":"lucy0001","chinese":"他们每人都携带了一千克毒品 我要你逮捕他们 拿到毒品","english":"Each one is carrying a kilo of drugs. I need you to arrest them and collect the substance.","startTime":2971330,"endTime":2975450},"packages":[{"id":"66807d37","captionId":"0c85efed","chinese":"","english":""},{"id":"7fca6c48","captionId":"0c85efed","chinese":"","english":""},{"id":"f824cc7a","captionId":"0c85efed","chinese":"","english":""},{"id":"a15611dc","captionId":"0c85efed","chinese":"","english":null},{"id":"4eef355a","captionId":"0c85efed","chinese":"","english":null}]},{"caption":{"id":"79e79b87","orderNo":442,"movieId":"lucy0001","chinese":"我稍后有用","english":"I'll need it later.","startTime":2975460,"endTime":2976630},"packages":[{"id":"71395c57","captionId":"79e79b87","chinese":"","english":""},{"id":"4427da50","captionId":"79e79b87","chinese":"","english":""},{"id":"e7901bd1","captionId":"79e79b87","chinese":"","english":""},{"id":"0458efe0","captionId":"79e79b87","chinese":"","english":null},{"id":"324afdeb","captionId":"79e79b87","chinese":"","english":null}]},{"caption":{"id":"6fe93469","orderNo":443,"movieId":"lucy0001","chinese":"什么样的毒品? 条状? 还是装在胶囊里?","english":"What form of these drugs in? Bars? Capsules?","startTime":2976700,"endTime":2979530},"packages":[{"id":"64a03baa","captionId":"6fe93469","chinese":"","english":""},{"id":"3833e50f","captionId":"6fe93469","chinese":"","english":""},{"id":"f07d5c1a","captionId":"6fe93469","chinese":"","english":""},{"id":"53e2e30c","captionId":"6fe93469","chinese":"","english":null},{"id":"9b57ac78","captionId":"6fe93469","chinese":"","english":null}]},{"caption":{"id":"fa910994","orderNo":444,"movieId":"lucy0001","chinese":"粉末 用塑料袋装着 藏在他们腹内","english":"Powder, hidden in plastic pouches inside their intestines.","startTime":2979680,"endTime":2983570},"packages":[{"id":"55749242","captionId":"fa910994","chinese":"","english":""},{"id":"35b2383a","captionId":"fa910994","chinese":"","english":""},{"id":"f52077f1","captionId":"fa910994","chinese":"","english":""},{"id":"aec2531d","captionId":"fa910994","chinese":"","english":null},{"id":"f0a36f2e","captionId":"fa910994","chinese":"","english":null}]},{"caption":{"id":"f9c55823","orderNo":445,"movieId":"lucy0001","chinese":"什么?","english":"Excuse me?","startTime":2983660,"endTime":2984650},"packages":[{"id":"e9b4173d","captionId":"f9c55823","chinese":"","english":""},{"id":"b41839c0","captionId":"f9c55823","chinese":"","english":""},{"id":"a3687aaa","captionId":"f9c55823","chinese":"","english":""},{"id":"642a3df4","captionId":"f9c55823","chinese":"","english":null},{"id":"439682ca","captionId":"f9c55823","chinese":"","english":null}]},{"caption":{"id":"85250b8a","orderNo":446,"movieId":"lucy0001","chinese":"取走的时候一定要小心 那粉末威力很大","english":"Make sure to be careful when you remove them. The product is very powerful.","startTime":2984660,"endTime":2987900},"packages":[{"id":"6aeafdbc","captionId":"85250b8a","chinese":"","english":""},{"id":"926e16ad","captionId":"85250b8a","chinese":"","english":""},{"id":"e7605c91","captionId":"85250b8a","chinese":"","english":""},{"id":"08e92159","captionId":"85250b8a","chinese":"","english":null},{"id":"f91a2b24","captionId":"85250b8a","chinese":"","english":null}]},{"caption":{"id":"acd077a6","orderNo":447,"movieId":"lucy0001","chinese":"相信我","english":"Believe me.","startTime":2994520,"endTime":2995670},"packages":[{"id":"66ecbf67","captionId":"acd077a6","chinese":"","english":""},{"id":"83149b6a","captionId":"acd077a6","chinese":"","english":""},{"id":"b642bda3","captionId":"acd077a6","chinese":"","english":""},{"id":"0ae882fe","captionId":"acd077a6","chinese":"","english":null},{"id":"e3e179b5","captionId":"acd077a6","chinese":"","english":null}]},{"caption":{"id":"8c402f9c","orderNo":448,"movieId":"lucy0001","chinese":"看到了吗?","english":"Got it?","startTime":2997190,"endTime":2998580},"packages":[{"id":"0ddf62ec","captionId":"8c402f9c","chinese":"","english":""},{"id":"b02173d4","captionId":"8c402f9c","chinese":"","english":""},{"id":"56526b00","captionId":"8c402f9c","chinese":"","english":""},{"id":"8655520d","captionId":"8c402f9c","chinese":"","english":null},{"id":"da2f6693","captionId":"8c402f9c","chinese":"","english":null}]},{"caption":{"id":"4e8cdc50","orderNo":449,"movieId":"lucy0001","chinese":"是的","english":"Yeah.","startTime":2998700,"endTime":2999730},"packages":[{"id":"a914a334","captionId":"4e8cdc50","chinese":"","english":""},{"id":"3394a461","captionId":"4e8cdc50","chinese":"","english":""},{"id":"cea348da","captionId":"4e8cdc50","chinese":"","english":""},{"id":"1d79e78c","captionId":"4e8cdc50","chinese":"","english":null},{"id":"e145a693","captionId":"4e8cdc50","chinese":"","english":null}]},{"caption":{"id":"bd376560","orderNo":450,"movieId":"lucy0001","chinese":"很好","english":"Good.","startTime":3000110,"endTime":3001330},"packages":[{"id":"d700c90d","captionId":"bd376560","chinese":"","english":""},{"id":"0cc6cf04","captionId":"bd376560","chinese":"","english":""},{"id":"c35d83a0","captionId":"bd376560","chinese":"","english":""},{"id":"64394954","captionId":"bd376560","chinese":"","english":null},{"id":"594d435f","captionId":"bd376560","chinese":"","english":null}]}]
